web3_py_tools/__init__.py
web3_py_tools-0.0.4.dist-info/METADATA
web3_py_tools-0.0.4.dist-info/WHEEL
web3_py_tools-0.0.4.dist-info/RECORD
