Metadata-Version: 2.1
Name: web3-py-tools
Version: 0.0.4
Summary: 
Author: pydevel
Author-email: ppydevel@gmail.com
Requires-Python: >=3.8
Classifier: Programming Language :: Python :: 3
Classifier: Programming Language :: Python :: 3.8
Classifier: Programming Language :: Python :: 3.9
Classifier: Programming Language :: Python :: 3.10
Classifier: Programming Language :: Python :: 3.11
Classifier: Programming Language :: Python :: 3.12
Requires-Dist: aiohttp (>=3.7.4.post0)
Requires-Dist: colorlog (==6.8.0)
Requires-Dist: eth-abi (>=4.0.0)
Requires-Dist: eth-account-api (>=1.0.0,<2.0.0)
Requires-Dist: eth-hash (>=0.5.1)
Requires-Dist: eth-typing (>=3.0.0)
Requires-Dist: eth-utils (>=2.1.0)
Requires-Dist: hexbytes (>=0.1.0,<0.4.0)
Requires-Dist: jsonschema (>=4.0.0)
Requires-Dist: lru-dict (>=1.1.6,<1.3.0)
Requires-Dist: protobuf (>=4.21.6)
Requires-Dist: pyunormalize (>=15.0.0)
Requires-Dist: requests (>=2.16.0)
Requires-Dist: typing-extensions (>=4.0.1)
Requires-Dist: web3 (>=5.0.0)
Requires-Dist: websockets (>=10.0.0)
